barcodeSpliter/__init__.py
barcodeSpliter/barcodeSpliter.py
barcodeSpliter-2.1.1.dist-info/LICENSE
barcodeSpliter-2.1.1.dist-info/METADATA
barcodeSpliter-2.1.1.dist-info/WHEEL
barcodeSpliter-2.1.1.dist-info/entry_points.txt
barcodeSpliter-2.1.1.dist-info/top_level.txt
barcodeSpliter-2.1.1.dist-info/RECORD
