Metadata-Version: 2.1
Name: barcodeSpliter
Version: 2.1.1
Summary: "barcodeSpliter" can use barcode label to         separate different samples in mixed-sample sequencing.
Home-page: https://github.com/atlasbioinfo/barcodeSpliter
Author: Haopeng Yu
Author-email: atlasbioin4@gmail.com
License: Apache-2.0
Classifier: Programming Language :: Python :: 3
Classifier: License :: OSI Approved :: Apache Software License
Classifier: Operating System :: OS Independent
Requires-Python: >=3.6
License-File: LICENSE
